dal_admin_filters/__init__.py
dal_admin_filters/static/dal_admin_filters/css/autocomplete-fix.css
dal_admin_filters/static/dal_admin_filters/js/forward-fix.js
dal_admin_filters/static/dal_admin_filters/js/querystring.js
dal_admin_filters/templates/dal_admin_filters/autocomplete-filter.html
dal_admin_filters-1.1.0.dist-info/LICENSE
dal_admin_filters-1.1.0.dist-info/METADATA
dal_admin_filters-1.1.0.dist-info/WHEEL
dal_admin_filters-1.1.0.dist-info/top_level.txt
dal_admin_filters-1.1.0.dist-info/RECORD
